src/__init__.py
src/config.py
src/db.sqlite3
src/decorators.py
src/descriptors.py
src/meta.py
src/server.py
src/server_database.py
src/server_gui.ui
src/test_server.py
src/logs/__init__.py
src/logs/config/__init__.py
src/logs/config/server_config_log.py
quickim_server-0.1.1.dist-info/METADATA
quickim_server-0.1.1.dist-info/WHEEL
quickim_server-0.1.1.dist-info/top_level.txt
quickim_server-0.1.1.dist-info/RECORD
